agentium/__init__.py
agentium/core/__init__.py
agentium/core/communicator.py
agentium/core/condenser.py
agentium/core/extractor.py
agentium/core/insight_generator.py
agentium/core/memory_helper.py
agentium/core/optimizer.py
agentium/core/rearranger.py
agentium/core/summarize_custom.py
agentium/core/template_manager.py
agentium/core/translator.py
agentium/core/workflow_helper.py
agentium/integrations/__init__.py
agentium/integrations/gemini.py
agentium/integrations/langchain.py
agentium/integrations/langgraph.py
agentium/utils/__init__.py
agentium/utils/logger_utils.py
agentium-1.1.0.dist-info/METADATA
agentium-1.1.0.dist-info/WHEEL
agentium-1.1.0.dist-info/top_level.txt
agentium-1.1.0.dist-info/RECORD
