Metadata-Version: 2.4
Name: agentium
Version: 1.1.0
Summary: A comprehensive toolkit for AI agent development and workflow orchestration with Gemini AI integration
Home-page: https://github.com/RNSsanjay/Agentium-Python-Library
Author: Sanjay N
Author-email: 2005sanjaynrs@gmail.com
Keywords: ai,agents,langchain,langgraph,gemini,nlp,automation,workflow,google-ai
Classifier: Development Status :: 4 - Beta
Classifier: Intended Audience :: Developers
Classifier: License :: OSI Approved :: MIT License
Classifier: Operating System :: OS Independent
Classifier: Programming Language :: Python :: 3
Classifier: Programming Language :: Python :: 3.8
Classifier: Programming Language :: Python :: 3.9
Classifier: Programming Language :: Python :: 3.10
Classifier: Programming Language :: Python :: 3.11
Classifier: Programming Language :: Python :: 3.12
Classifier: Topic :: Software Development :: Libraries :: Python Modules
Classifier: Topic :: Scientific/Engineering :: Artificial Intelligence
Classifier: Topic :: Text Processing :: Linguistic
Classifier: Topic :: Communications
Requires-Python: >=3.8
Requires-Dist: numpy>=1.21.0
Requires-Dist: pandas>=1.3.0
Requires-Dist: requests>=2.25.0
Requires-Dist: pydantic>=2.0.0
Requires-Dist: typing-extensions>=4.0.0
Requires-Dist: python-dotenv>=0.19.0
Requires-Dist: asyncio-throttle>=1.0.0
Requires-Dist: aiohttp>=3.8.0
Requires-Dist: openai>=1.0.0
Requires-Dist: anthropic>=0.3.0
Requires-Dist: google-generativeai>=0.3.0
Requires-Dist: tiktoken>=0.4.0
Requires-Dist: beautifulsoup4>=4.9.0
Requires-Dist: lxml>=4.6.0
Requires-Dist: PyYAML>=6.0
Requires-Dist: Jinja2>=3.0.0
Requires-Dist: redis>=4.0.0
Requires-Dist: sqlite3
Requires-Dist: logging
Requires-Dist: json5>=0.9.0
Requires-Dist: dateutil>=2.8.0
Requires-Dist: textstat>=0.7.0
Requires-Dist: scikit-learn>=1.0.0
Provides-Extra: dev
Requires-Dist: pytest>=7.0; extra == "dev"
Requires-Dist: pytest-cov>=4.0; extra == "dev"
Requires-Dist: black>=22.0; extra == "dev"
Requires-Dist: flake8>=5.0; extra == "dev"
Requires-Dist: mypy>=0.991; extra == "dev"
Provides-Extra: langchain
Requires-Dist: langchain>=0.1.0; extra == "langchain"
Requires-Dist: langchain-community>=0.0.10; extra == "langchain"
Provides-Extra: langgraph
Requires-Dist: langgraph>=0.0.20; extra == "langgraph"
Provides-Extra: ai
Requires-Dist: google-generativeai>=0.3.0; extra == "ai"
Dynamic: author
Dynamic: author-email
Dynamic: classifier
Dynamic: description
Dynamic: description-content-type
Dynamic: home-page
Dynamic: keywords
Dynamic: provides-extra
Dynamic: requires-dist
Dynamic: requires-python
Dynamic: summary
